{
	"nome": "Polo Giuseppe Veronesi",
	"sede_principale_MIUR": "TNCF002001",

	"sedi": [
		{
			"nome": "CFP G. Veronesi",
			"codice_MIUR": "TNCF002001",

            "responsabile_orientamento": "Claudio Porcelluzzi",

			"posizione": {
				"indirizzo": "Piazzale Orsi, 1 - ROVERETO",
				"latitudine": "45.891789",
				"longitudine": "11.035101"
			},

            "indirizzi_studi": [
                {
                    "nome": "Operatore meccatronico - qualifica triennale",
                    "link": "https://drive.google.com/drive/folders/1dBPRveDcBrhPwmq0wI3i4c8Wx4t0G1bV?usp=drive_link"
                },
                {
                    "nome": "Operatore meccanico - qualifica triennale",
                    "link": "https://drive.google.com/drive/folders/1k5C33yld6w3-tsfgThVbHXGZBXfsvFbT?usp=drive_link"
                },
                {
                    "nome": "Operatore elettrico - qualifica triennale",
                    "link": "https://drive.google.com/drive/folders/1tOElINcSHWQ9TW47ayGOh9GZAxGZMSga?usp=drive_link"
                },
                {
                    "nome": "Operatore della carpenteria metallica - qualifica triennale",
                    "link": "https://drive.google.com/drive/folders/1VeSq5KgofiArVBGRSJGbMlmpDirwT0CK?usp=drive_link"
                },
                {
                    "nome": "Tecnico dell'automazione industriale - diploma professionale di quarto anno",
                    "link": "https://drive.google.com/file/d/1bSvoJX8lsVT-DuDrajxjGKJwtLoTDcxx/view?usp=drive_link"
                },
                {
                    "nome": "Tecnico della programmazione e gestione di impianti di produzione - diploma professionale di quarto anno",
                    "link": "https://drive.google.com/file/d/1bSvoJX8lsVT-DuDrajxjGKJwtLoTDcxx/view?usp=drive_link"
                },
                {
                    "nome": "Diploma di Istituto Professionale Manutenzione ed Assistenza Tecnica - Maturità (Quinto anno CAPES)",
                    "link": "https://drive.google.com/drive/folders/1cjTs5Izl9rxw-3q8fsqrJUpJ6HpHb5Ap?usp=drive_link"
                },
                {
                    "nome": "Diploma di Istituto Professionale Tecnico Industria e Artigianato per il Made in Italy - Maturità (Quinto anno CAPES)",
                    "link": "https://drive.google.com/drive/folders/1P8U5szaibLJJafR6lnezNQ-ww5-2MlO8?usp=drive_link"
                }
            ],

			"website": "https://www.poloveronesi.it",
			"contacts": {
				"mail": [
                    {
                        "description": "orientamento",
                        "mail": "orientamento@poloveronesi.it"
                    },
					{
						"description": "istituto",
						"mail": "iscrizioni.veronesi@pec.it"
					},
					{
						"description": "segreteria",
						"mail": "segreteria.dir@cfpgveronesi.it"
					}
				],
				"phone": [
					{
						"description": "telefono",
						"numero": "+39 0464 433484"
					},
					{
						"description": "fax",
						"numero": "+39 0464 436873"
					}
				]
			}
		},

		{
			"nome": "MADE++",
			"codice_MIUR": "TNCF002001-B",

            "responsabile_orientamento": "Claudio Porcelluzzi",

			"posizione": {
				"indirizzo": "Via Fortunato Zeni, 8 - 38068 ROVERETO",
				"latitudine": "45.891255",
				"longitudine": "11.02986"
			},

            "indirizzi_studi": [
                {
                    "nome": "MADE++ - Tecnico della Modellazione e Fabbricazione Digitale (Diploma quadriennale)",
                    "link": "https://drive.google.com/file/d/1PwTigZmUfiGbYs7RGkbB0_tb1wVw4aPB/view?usp=drive_link"
                }
			],

			"website": "https://www.poloveronesi.it",
			"contacts": {
				"mail": [
                    {
                        "description": "orientamento",
                        "mail": "orientamento@poloveronesi.it"
                    },
					{
						"description": "istituto",
						"mail": "iscrizioni.veronesi@pec.it"
					},
					{
						"description": "segreteria",
						"mail": "segreteria.dir@cfpgveronesi.it"
					}
				],
				"phone": [
					{
						"description": "telefono",
						"numero": "+39 0464 433484"
					},
					{
						"description": "fax",
						"numero": "+39 0464 436873"
					}
				]
			}
		},

		{
			"nome": "Liceo Steam International",
			"codice_MIUR": "TNPSID500S",

            "responsabile_orientamento": "Elena Trainotti",

			"posizione": {
				"indirizzo": "Via Madonna del Monte, 6 - ROVERETO",
				"latitudine": "45.881998",
				"longitudine": "11.044591"
			},

            "indirizzi_studi": [
                {
                    "nome": "Liceo Scientifico - scienze applicate",
                    "link": "https://drive.google.com/drive/folders/1Td292FMJcxNk1qC9SojDZky2AB4sfkBc"
                }
            ],

			"website": "https://www.liceosteam.it",
			"contacts": {
				"mail": [
				    {
                        "description": "orientamento",
                        "mail": "info@liceosteam.it"
                    },
					{
						"description": "istituto",
						"mail": "iscrizioni.veronesi@pec.it"
					},
					{
						"description": "segreteria",
						"mail": "segreteria.dir@cfpgveronesi.it"
					}
				],
				"phone": [
					{
						"description": "telefono",
						"numero": "+39 0464 433484"
					},
					{
						"description": "fax",
						"numero": "+39 0464 436873"
					}
				]
			}
		}
	]
}